limecore/messaging/rabbitmq/__init__.py
limecore/messaging/rabbitmq/configuration.py
limecore/messaging/rabbitmq/configuration_builder.py
limecore/messaging/rabbitmq/module.py
limecore/messaging/rabbitmq/publisher.py
limecore/messaging/rabbitmq/subscriber.py
limecore_messaging_rabbitmq-0.2.0.dist-info/LICENSE.txt
limecore_messaging_rabbitmq-0.2.0.dist-info/METADATA
limecore_messaging_rabbitmq-0.2.0.dist-info/WHEEL
limecore_messaging_rabbitmq-0.2.0.dist-info/top_level.txt
limecore_messaging_rabbitmq-0.2.0.dist-info/RECORD
