Metadata-Version: 2.1
Name: limecore-messaging-rabbitmq
Version: 0.2.0
Summary: limecore: Messaging (RabbitMQ)
Home-page: https://github.com/limecore/messaging-rabbitmq
Author: Daniel Bradberry
Author-email: daniel@danielbradberry.com
License: MIT
Platform: UNKNOWN
Classifier: Programming Language :: Python :: 3
Classifier: License :: OSI Approved :: MIT License
Classifier: Operating System :: OS Independent
Requires-Python: >=3.7
Requires-Dist: amqpstorm
Requires-Dist: injector
Requires-Dist: limecore-core (>=0.2.0)
Requires-Dist: limecore-core-configuration
Requires-Dist: limecore-messaging-api (>=0.2.1)
